LICENSE
MANIFEST.in
README.rst
setup.py
django_restart.egg-info/PKG-INFO
django_restart.egg-info/SOURCES.txt
django_restart.egg-info/dependency_links.txt
django_restart.egg-info/requires.txt
django_restart.egg-info/top_level.txt
restart/__init__.py
restart/admin.py
restart/models.py
restart/static/admin/css/restart.css
restart/static/admin/js/restart.js
restart/templates/admin/base.html
restart/templates/admin/inc/extrahead.html
restart/templates/restart/widget.html
restart/templatetags/__init__.py
restart/templatetags/__init__.pyc
restart/templatetags/restart_tags.py
restart/templatetags/restart_tags.pyc