Metadata-Version: 1.1
Name: django-restart
Version: 0.2.8.4
Summary: A simple Django app to let admins restart the application
Home-page: https://bitbucket.org/lvlup/django-restart/overview
Author: Allan Brown
Author-email: allan@thisislevelup.com
License: BSD License
Platform: UNKNOWN
Classifier: Environment :: Web Environment
Classifier: Framework :: Django
Classifier: Intended Audience :: Developers
Classifier: License :: OSI Approved :: BSD License
Classifier: Operating System :: OS Independent
Classifier: Programming Language :: Python
Classifier: Programming Language :: Python :: 2.6
Classifier: Programming Language :: Python :: 2.7
Classifier: Topic :: Internet :: WWW/HTTP
Classifier: Topic :: Internet :: WWW/HTTP :: Dynamic Content
